control_plane_openapi_mcp/__init__.py
control_plane_openapi_mcp/_version.py
control_plane_openapi_mcp/config.py
control_plane_openapi_mcp/server.py
control_plane_openapi_mcp/tools.py
control_plane_openapi_mcp/core/__init__.py
control_plane_openapi_mcp/core/cache.py
control_plane_openapi_mcp/core/models.py
control_plane_openapi_mcp/core/search.py
control_plane_openapi_mcp/core/service.py
control_plane_openapi_mcp/core/spec_loader.py
control_plane_openapi_mcp/core/spec_processor.py
control_plane_openapi_mcp/prompts/__init__.py
control_plane_openapi_mcp/prompts/api_script_guide.md
control_plane_openapi_mcp/prompts/api_script_prompt.py
control_plane_openapi_mcp/utils/__init__.py
control_plane_openapi_mcp/utils/client.py
control_plane_openapi_mcp/utils/schema_extractor.py
control_plane_openapi_mcp-1.0.1.dist-info/METADATA
control_plane_openapi_mcp-1.0.1.dist-info/WHEEL
control_plane_openapi_mcp-1.0.1.dist-info/entry_points.txt
control_plane_openapi_mcp-1.0.1.dist-info/top_level.txt
control_plane_openapi_mcp-1.0.1.dist-info/RECORD
