Metadata-Version: 2.4
Name: control-plane-openapi-mcp
Version: 1.0.1
Summary: MCP server for Facets Control Plane OpenAPI specification
Author-email: Anuj Hydrabadi <anuj.hydrabadi@facets.cloud>
License: MIT
Project-URL: Homepage, https://github.com/Facets-cloud/control-plane-openapi-mcp
Project-URL: Bug Tracker, https://github.com/Facets-cloud/control-plane-openapi-mcp/issues
Project-URL: Documentation, https://github.com/Facets-cloud/control-plane-openapi-mcp#readme
Keywords: Facets,MCP,OpenAPI,Python
Classifier: Programming Language :: Python :: 3
Classifier: Programming Language :: Python :: 3.11
Classifier: Programming Language :: Python :: 3.12
Classifier: Programming Language :: Python :: 3.13
Classifier: License :: OSI Approved :: MIT License
Classifier: Operating System :: OS Independent
Classifier: Topic :: Software Development :: Libraries :: Python Modules
Classifier: Intended Audience :: Developers
Classifier: Development Status :: 4 - Beta
Requires-Python: >=3.11
Requires-Dist: mcp[cli]
Requires-Dist: requests>=2.31.0
Requires-Dist: jsonref>=1.1.0
Requires-Dist: pydantic>=2.0
Requires-Dist: fuzzywuzzy>=0.18.0
Requires-Dist: python-levenshtein>=0.21.0
